{
  "book": "Salmos",
  "bookSlug": "salmos",
  "chapter": 81,
  "version": "RV1960",
  "verses": [
    {
      "number": 1,
      "text": "/nCantad con gozo a Dios, fortaleza nuestra; /nAl Dios de Jacob aclamad con júbilo."
    },
    {
      "number": 2,
      "text": "/nEntonad canción, y tañed el pandero, /nEl arpa deliciosa y el salterio."
    },
    {
      "number": 3,
      "text": "/nTocad la trompeta en la nueva luna, /nEn el día señalado, en el día de nuestra fiesta solemne."
    },
    {
      "number": 4,
      "text": "/nPorque estatuto es de Israel, /nOrdenanza del Dios de Jacob."
    },
    {
      "number": 5,
      "text": "/nLo constituyó como testimonio en José /nCuando salió por la tierra de Egipto. /nOí lenguaje que no entendía;"
    },
    {
      "number": 6,
      "text": "/nAparté su hombro de debajo de la carga; /nSus manos fueron descargadas de los cestos."
    },
    {
      "number": 7,
      "text": "/nEn la calamidad clamaste, y yo te libré; /nTe respondí en lo secreto del trueno; /nTe probé junto a las aguas de Meriba. Selah"
    },
    {
      "number": 8,
      "text": "/nOye, pueblo mío, y te amonestaré. /nIsrael, si me oyeres,"
    },
    {
      "number": 9,
      "text": "/nNo habrá en ti dios ajeno, /nNi te inclinarás a dios extraño."
    },
    {
      "number": 10,
      "text": "/nYo soy Jehová tu Dios, /nQue te hice subir de la tierra de Egipto; /nAbre tu boca, y yo la llenaré."
    },
    {
      "number": 11,
      "text": "/nPero mi pueblo no oyó mi voz, /nE Israel no me quiso a mí."
    },
    {
      "number": 12,
      "text": "/nLos dejé, por tanto, a la dureza de su corazón; /nCaminaron en sus propios consejos."
    },
    {
      "number": 13,
      "text": "/n¡Oh, si me hubiera oído mi pueblo, /nSi en mis caminos hubiera andado Israel!"
    },
    {
      "number": 14,
      "text": "/nEn un momento habría yo derribado a sus enemigos, /nY vuelto mi mano contra sus adversarios."
    },
    {
      "number": 15,
      "text": "/nLos que aborrecen a Jehová se le habrían sometido, /nY el tiempo de ellos sería para siempre."
    },
    {
      "number": 16,
      "text": "/nLes sustentaría Dios con lo mejor del trigo, /nY con miel de la peña les saciaría."
    }
  ]
}